rot2prog/__init__.py
rot2prog/rot2prog.py
rot2prog/utils/__init__.py
rot2prog/utils/run.py
rot2prog/utils/sim.py
rot2prog-0.0.10.dist-info/licenses/LICENSE.txt
rot2prog-0.0.10.dist-info/METADATA
rot2prog-0.0.10.dist-info/WHEEL
rot2prog-0.0.10.dist-info/top_level.txt
rot2prog-0.0.10.dist-info/RECORD
