Metadata-Version: 2.4
Name: rot2prog
Version: 0.0.10
Summary: A python interface to the Alfa ROT2Prog Controller.
Home-page: https://github.com/tj-scherer/rot2prog
Author: TJ Scherer
Author-email: tjtractorboy@gmail.com
Project-URL: Bug Tracker, https://github.com/tj-scherer/rot2prog/issues
Classifier: Programming Language :: Python :: 3.10
Classifier: License :: OSI Approved :: MIT License
Classifier: Operating System :: OS Independent
Classifier: Topic :: Scientific/Engineering :: Astronomy
Requires-Python: >=3.10
License-File: LICENSE.txt
Requires-Dist: pyserial
Dynamic: author
Dynamic: author-email
Dynamic: classifier
Dynamic: description
Dynamic: description-content-type
Dynamic: home-page
Dynamic: license-file
Dynamic: project-url
Dynamic: requires-dist
Dynamic: requires-python
Dynamic: summary
